Adyen/__init__.py
Adyen/client.py
Adyen/exceptions.py
Adyen/httpclient.py
Adyen/settings.py
Adyen/util.py
AdyenAntoni-1.0.0.dist-info/LICENSE.md
AdyenAntoni-1.0.0.dist-info/METADATA
AdyenAntoni-1.0.0.dist-info/WHEEL
AdyenAntoni-1.0.0.dist-info/top_level.txt
AdyenAntoni-1.0.0.dist-info/RECORD
