Metadata-Version: 2.1
Name: AdyenAntoni
Version: 1.0.0
Summary: Adyen Python Api
Home-page: https://github.com/Adyen/adyen-python-api-library
Author: AdyenAntoni
Author-email: support@adyen.com
Maintainer: AdyenAntoni
Maintainer-email: support@adyen.com
Keywords: payments,adyen,fintech
Classifier: Development Status :: 5 - Production/Stable
Classifier: Intended Audience :: Developers
Classifier: Topic :: Software Development :: Libraries
Classifier: License :: OSI Approved :: MIT License
Classifier: Programming Language :: Python :: 2.7
Classifier: Programming Language :: Python :: 3.6
License-File: LICENSE.md
